monstra/__init__.py
monstra/_version.py
monstra-0.1.0.data/data/share/jupyter/labextensions/jupyter-monstra/build_log.json
monstra-0.1.0.data/data/share/jupyter/labextensions/jupyter-monstra/package.json
monstra-0.1.0.data/data/share/jupyter/labextensions/jupyter-monstra/static/lib_index_js.cc348909962c26412c47.js
monstra-0.1.0.data/data/share/jupyter/labextensions/jupyter-monstra/static/lib_index_js.cc348909962c26412c47.js.map
monstra-0.1.0.data/data/share/jupyter/labextensions/jupyter-monstra/static/remoteEntry.4cb5e37b4822daea74a3.js
monstra-0.1.0.data/data/share/jupyter/labextensions/jupyter-monstra/static/remoteEntry.4cb5e37b4822daea74a3.js.map
monstra-0.1.0.data/data/share/jupyter/labextensions/jupyter-monstra/static/style.js
monstra-0.1.0.data/data/share/jupyter/labextensions/jupyter-monstra/static/style_index_js.68ff4e6136b7945efda6.js
monstra-0.1.0.data/data/share/jupyter/labextensions/jupyter-monstra/static/style_index_js.68ff4e6136b7945efda6.js.map
monstra-0.1.0.data/data/share/jupyter/labextensions/jupyter-monstra/install.json
monstra-0.1.0.dist-info/METADATA
monstra-0.1.0.dist-info/WHEEL
monstra-0.1.0.dist-info/licenses/LICENSE
monstra-0.1.0.dist-info/RECORD
